phdsp/__init__.py
phdsp/main.py
phdsp-0.0.1.dist-info/LICENSE
phdsp-0.0.1.dist-info/METADATA
phdsp-0.0.1.dist-info/WHEEL
phdsp-0.0.1.dist-info/RECORD
